Metadata-Version: 1.0
Name: fourier-integrals
Version: 0.1
Summary: Gaussian distributions and Binomial distributions
Home-page: UNKNOWN
Author:  Vernon Hendon
Author-email: spaceghost06@yahoo.com
License: UNKNOWN
Platform: UNKNOWN
